LICENSE
MANIFEST.in
README.md
setup.py
./.gitignore
./CODE_OF_CONDUCT.md
./CONTRIBUTING.md
./LICENSE
./MANIFEST.in
./README.md
./logging.json
./requirements.txt
./setup.py
./.git/FETCH_HEAD
./.git/HEAD
./.git/config
./.git/description
./.git/index
./.git/hooks/applypatch-msg.sample
./.git/hooks/commit-msg.sample
./.git/hooks/fsmonitor-watchman.sample
./.git/hooks/post-update.sample
./.git/hooks/pre-applypatch.sample
./.git/hooks/pre-commit.sample
./.git/hooks/pre-merge-commit.sample
./.git/hooks/pre-push.sample
./.git/hooks/pre-rebase.sample
./.git/hooks/pre-receive.sample
./.git/hooks/prepare-commit-msg.sample
./.git/hooks/push-to-checkout.sample
./.git/hooks/update.sample
./.git/info/exclude
./.git/logs/HEAD
./.git/logs/refs/heads/master
./.git/logs/refs/remotes/origin/gh-pages
./.git/logs/refs/remotes/origin/master
./.git/logs/refs/remotes/origin/pc.gui
./.git/objects/pack/pack-3c528c1f8636a2c5a0b0bd9e7db80029f9809c05.idx
./.git/objects/pack/pack-3c528c1f8636a2c5a0b0bd9e7db80029f9809c05.pack
./.git/refs/heads/master
./.git/refs/remotes/origin/gh-pages
./.git/refs/remotes/origin/master
./.git/refs/remotes/origin/pc.gui
./.git/refs/tags/v0.1
./.github/ISSUE_TEMPLATE/bug_report.md
./.github/ISSUE_TEMPLATE/feature_request.md
./.github/workflows/pull-request.yml
./.github/workflows/push.yml
./ifra/__init__.py
./ifra/_version.py
./ifra/actor.py
./ifra/aggregations.py
./ifra/aggregator.py
./ifra/central_server.py
./ifra/configs.py
./ifra/datapreps.py
./ifra/decorator.py
./ifra/diff_privacy.py
./ifra/duplicated_rules_updater.py
./ifra/fitters.py
./ifra/loader.py
./ifra/messenger.py
./ifra/node.py
./ifra/node_model_updaters.py
./ifra/plot.py
./ifra/setup_logger.py
./ifra/train_test_split.py
./ifra.egg-info/PKG-INFO
./ifra.egg-info/SOURCES.txt
./ifra.egg-info/dependency_links.txt
./ifra.egg-info/requires.txt
./ifra.egg-info/top_level.txt
./tests/__init__.py
./tests/conftest.py
./tests/alternates/__init__.py
./tests/alternates/dataprep.py
./tests/alternates/fitter.py
./tests/alternates/updater.py
./tests/data/aggregator_configs.json
./tests/data/central_configs.json
./tests/data/make_data.py
ifra.egg-info/PKG-INFO
ifra.egg-info/SOURCES.txt
ifra.egg-info/dependency_links.txt
ifra.egg-info/requires.txt
ifra.egg-info/top_level.txt