Metadata-Version: 2.1
Name: ifra
Version: 0.1.257
Summary: Interpretable Federated Rule Algorithm
Home-page: https://github.com/Advestis/ifra
Author: Philippe COTTE
Author-email: pcotte@advestis.com
License: UNKNOWN
Platform: UNKNOWN
Classifier: Programming Language :: Python :: 3.7
Classifier: Programming Language :: Python :: 3.8
Classifier: Programming Language :: Python :: 3.9
Classifier: License :: OSI Approved :: GNU General Public License v3 (GPLv3)
Classifier: Operating System :: Unix
Classifier: Development Status :: 5 - Production/Stable
Requires-Python: >=3.7
License-File: LICENSE
